cs_telegram_bot/__init__.py
cs_telegram_bot/api.py
cs_telegram_bot/get_chat_ids.py
cs_telegram_bot_api-0.0.9.dist-info/METADATA
cs_telegram_bot_api-0.0.9.dist-info/WHEEL
cs_telegram_bot_api-0.0.9.dist-info/top_level.txt
cs_telegram_bot_api-0.0.9.dist-info/RECORD
