Metadata-Version: 2.1
Name: cs-telegram-bot-api
Version: 0.0.9
Summary: Telegram Bot API Wrapper
Author: Richard
Author-email: <rich_swainson@hotmail.co.uk>
Keywords: telegram,bot,api,wrapper
Classifier: Development Status :: 5 - Production/Stable
Classifier: Intended Audience :: Developers
Classifier: Programming Language :: Python :: 3
Classifier: Operating System :: OS Independent
Requires-Dist: requests
Requires-Dist: psycopg2
